sauna/__init__.py
sauna/main.py
sauna/scheduler.py
sauna/commands/__init__.py
sauna/commands/ext/__init__.py
sauna/commands/ext/list.py
sauna/commands/ext/status.py
sauna/consumers/__init__.py
sauna/consumers/base.py
sauna/consumers/ext/__init__.py
sauna/consumers/ext/home_assistant_mqtt.py
sauna/consumers/ext/http.py
sauna/consumers/ext/http_icinga.py
sauna/consumers/ext/http_server.py
sauna/consumers/ext/nsca.py
sauna/consumers/ext/stdout.py
sauna/consumers/ext/tcp_server.py
sauna/consumers/ext/http_server/__init__.py
sauna/consumers/ext/http_server/dashboard_html.py
sauna/consumers/ext/http_server/html.py
sauna/plugins/__init__.py
sauna/plugins/base.py
sauna/plugins/ext/__init__.py
sauna/plugins/ext/apt.py
sauna/plugins/ext/command.py
sauna/plugins/ext/disk.py
sauna/plugins/ext/disque.py
sauna/plugins/ext/dummy.py
sauna/plugins/ext/http.py
sauna/plugins/ext/http_json.py
sauna/plugins/ext/hwmon.py
sauna/plugins/ext/load.py
sauna/plugins/ext/mdstat.py
sauna/plugins/ext/memcached.py
sauna/plugins/ext/memory.py
sauna/plugins/ext/network.py
sauna/plugins/ext/ntpd.py
sauna/plugins/ext/postfix.py
sauna/plugins/ext/processes.py
sauna/plugins/ext/puppet_agent.py
sauna/plugins/ext/redis.py
sauna/plugins/ext/simple_domain.py
sauna/plugins/ext/supervisor.py
sauna/plugins/ext/tcp.py
sauna-0.0.19.dist-info/LICENSE
sauna-0.0.19.dist-info/METADATA
sauna-0.0.19.dist-info/WHEEL
sauna-0.0.19.dist-info/entry_points.txt
sauna-0.0.19.dist-info/top_level.txt
sauna-0.0.19.dist-info/RECORD
