Metadata-Version: 2.1
Name: sauna
Version: 0.0.19
Summary: Daemon that runs and reports health checks
Home-page: https://github.com/NicolasLM/sauna
Author: Nicolas Le Manchet
Author-email: nicolas@lemanchet.fr
License: BSD
Keywords: monitoring health checks nagios shinken
Classifier: Development Status :: 3 - Alpha
Classifier: Environment :: Console
Classifier: Intended Audience :: System Administrators
Classifier: Topic :: System :: Monitoring
Classifier: Topic :: System :: Systems Administration
Classifier: License :: OSI Approved :: BSD License
Classifier: Programming Language :: Python :: 3
Classifier: Programming Language :: Python :: 3 :: Only
Classifier: Programming Language :: Python :: 3.6
Classifier: Programming Language :: Python :: 3.7
Classifier: Programming Language :: Python :: 3.8
Classifier: Programming Language :: Python :: 3.9
Classifier: Programming Language :: Python :: 3.10
License-File: LICENSE
Requires-Dist: docopt
Requires-Dist: PyYAML
Provides-Extra: tests
Requires-Dist: pytest ; extra == 'tests'
Requires-Dist: pycodestyle ; extra == 'tests'
Requires-Dist: requests-mock ; extra == 'tests'
Requires-Dist: pymdstat ; extra == 'tests'
Requires-Dist: jsonpath-rw ; extra == 'tests'
Requires-Dist: psutil ; extra == 'tests'
